{
  "snapshot_time": "2026-07-01 18:18:00",
  "a_stock": {
    "沪深300": {
      "symbol": "sh000300",
      "price": 4958.98,
      "prev_close": 4979.43,
      "change_pct": -0.41,
      "as_of": "20260701161407"
    },
    "中证500": {
      "symbol": "sh000905",
      "price": 9028.93,
      "prev_close": 9031.38,
      "change_pct": -0.03,
      "as_of": "20260701161413"
    },
    "中证1000": {
      "symbol": "sh000852",
      "price": 8876.63,
      "prev_close": 8809.79,
      "change_pct": 0.76,
      "as_of": "20260701161413"
    }
  },
  "a_stock_industry": {
    "半导体": {
      "symbol": "sh000827",
      "price": 1922.89,
      "prev_close": 1947.04,
      "change_pct": -1.24,
      "as_of": "20260701161413"
    },
    "新能源车": {
      "symbol": "sz399976",
      "price": 4441.29,
      "prev_close": 4393.97,
      "change_pct": 1.08,
      "as_of": "20260701161421"
    },
    "消费": {
      "symbol": "sh000932",
      "price": 11921.47,
      "prev_close": 11658.46,
      "change_pct": 2.26,
      "as_of": "20260701161413"
    },
    "医药": {
      "symbol": "sh000933",
      "price": 7612.73,
      "prev_close": 7350.44,
      "change_pct": 3.57,
      "as_of": "20260701161413"
    },
    "银行": {
      "symbol": "sh000934",
      "price": 5512.07,
      "prev_close": 5366.87,
      "change_pct": 2.71,
      "as_of": "20260701161413"
    },
    "高股息红利": {
      "symbol": "sh000922",
      "price": 5108.21,
      "prev_close": 5022.46,
      "change_pct": 1.71,
      "as_of": "20260701161447"
    }
  },
  "hk_stock": {
    "恒生科技": {
      "symbol": "hkHSTECH",
      "price": 4472.23,
      "prev_close": 4393.01,
      "change_pct": 1.8,
      "as_of": "2026/06/30 16:08:28"
    },
    "港股高股息": {
      "symbol": "hkHSCEI",
      "price": 7558.3,
      "prev_close": 7605.34,
      "change_pct": -0.62,
      "as_of": "2026/06/30 16:08:28"
    }
  },
  "us_stock": {
    "纳斯达克100": {
      "symbol": "^NDX",
      "price": 30276.3496,
      "prev_close": 29774.75,
      "change_pct": 1.68,
      "as_of": "2026-06-30"
    },
    "标普500": {
      "symbol": "^GSPC",
      "price": 7499.3599,
      "prev_close": 7440.4302,
      "change_pct": 0.79,
      "as_of": "2026-06-30"
    }
  },
  "bonds": {
    "美国国债10Y": {
      "symbol": "^TNX",
      "price": 4.372,
      "prev_close": 4.392,
      "change_pct": -0.46,
      "as_of": "2026-06-26",
      "yield_pct": 0.437
    }
  },
  "commodities": {
    "黄金": {
      "symbol": "GC=F",
      "price": 4002.1001,
      "prev_close": 4022.8999,
      "change_pct": -0.52,
      "as_of": "2026-07-01"
    },
    "原油WTI": {
      "symbol": "CL=F",
      "price": 68.93,
      "prev_close": 69.5,
      "change_pct": -0.82,
      "as_of": "2026-07-01"
    },
    "比特币": {
      "symbol": "BTC-USD",
      "price": 58698.6602,
      "prev_close": 58558.8594,
      "change_pct": 0.24,
      "as_of": "2026-07-01"
    }
  },
  "fx": {
    "美元人民币现金": {
      "symbol": "CNY=X",
      "price": 6.7828,
      "prev_close": 6.7936,
      "change_pct": -0.16,
      "as_of": "2026-07-01"
    }
  },
  "china_macro": {
    "PMI制造业": {
      "value": 49.4,
      "as_of": "2025-08-31"
    }
  },
  "fetch_errors": [
    "[中债收益率] 超时（>10.0s）",
    "[宏观-CPI同比] 超时（>10.0s）",
    "[宏观-M2同比] 超时（>10.0s）"
  ],
  "sources_used": [
    "tencent",
    "akshare",
    "yfinance"
  ]
}